{
  "subtitle": "Fantastic and Premium Clients",
  "title": "We've had the honor of partnering with a diverse clientele.",
  "items": [
    {
      "link": "https://www.lutron.com/en-US/pages/default.aspx",
      "label": "Visit Website",
      "image": "/images/z51.png"
    },
    {
      "link": "https://www.alcatelmobile.com/",
      "label": "Visit Website",
      "image": "/images/008.png"
    },
    {
      "link": "http://www.changhongglobal.net/about.html",
      "label": "Visit Website",
      "image": "/images/z7.svg.png"
    },
    {
      "link": "https://www.zulily.com",
      "label": "Visit Website",
      "image": "/images/z9.png"
    },
    {
      "link": "https://www.canadacomputers.com/",
      "label": "Visit Website",
      "image": "/images/z2.png"
    },
    {
      "link": "https://technation.io/",
      "label": "Visit Website",
      "image": "/images/tech.png"
    },
    {
      "link": "https://scalemedia.com/",
      "label": "Visit Website",
      "image": "/images/007.png"
    },
    {
      "link": "https://www.tdk.com/en/index.html",
      "label": "Visit Website",
      "image": "/images/tdk.png"
    }
  ]
}
